task1_rng/__init__.py
task1_rng/__main__.py
task1_rng/random_generator.py
proton_task1_rng-1.0.0.dist-info/METADATA
proton_task1_rng-1.0.0.dist-info/WHEEL
proton_task1_rng-1.0.0.dist-info/entry_points.txt
proton_task1_rng-1.0.0.dist-info/top_level.txt
proton_task1_rng-1.0.0.dist-info/RECORD
