Metadata-Version: 2.1
Name: proton-task1-rng
Version: 1.0.0
Summary: Generate a random number from a discrete distribution
Home-page: UNKNOWN
Author: Cyril van Schreven
Author-email: cyril.schreven@gmail.com
License: UNKNOWN
Platform: UNKNOWN
Classifier: Programming Language :: Python :: 3
Classifier: Programming Language :: Python :: 3.8
